MANIFEST.in
README.md
setup.py
dash-materialsintelligence.egg-info/PKG-INFO
dash-materialsintelligence.egg-info/SOURCES.txt
dash-materialsintelligence.egg-info/dependency_links.txt
dash-materialsintelligence.egg-info/top_level.txt
dash_materialsintelligence/__init__.py
dash_materialsintelligence/bundle.js
dash_materialsintelligence/metadata.json
dash_materialsintelligence/version.py