Metadata-Version: 1.0
Name: dash-materialsintelligence
Version: 0.0.7
Summary: Dash UI component suite for materialsintelligence project
Home-page: UNKNOWN
Author: vtshitoyan
Author-email: UNKNOWN
License: MIT
Platform: UNKNOWN
